nextrngbook-0.1.0.post1.dist-info/WHEEL
nextrngbook-0.1.0.post1.dist-info/METADATA
nextrngbook-0.1.0.post1.dist-info/RECORD
nextrngbook-0.1.0.post1.dist-info/top_level.txt
nextrngbook-0.1.0.post1.dist-info/licenses/LICENSE
nextrngbook/__init__.py
nextrngbook/dx_generator/_dx_generator32.pyx
nextrngbook/dx_generator/_dx_generator32.cpython-39-x86_64-linux-gnu.so
nextrngbook/dx_generator/__init__.py
nextrngbook/dx_generator/src/dx_k_s_32.c
nextrngbook/dx_generator/src/dx_k_s_32.h
nextrngbook/dx_generator/data/dx32_parameters.csv
