Metadata-Version: 2.4
Name: nextrngbook
Version: 0.1.0.post1
Summary: A Python Random Number Generation Package for RNG Book
Author-email: "Lin, Chin-Tung" <tonylin8704@gmail.com>
Maintainer-email: "Cai, Meng-Xun" <rr991370@gmail.com>
License-Expression: MIT
Project-URL: Homepage, https://nextrngbook.github.io/nextrngbook/
Project-URL: Repository, https://github.com/nextrngbook/nextrngbook
Project-URL: Issues, https://github.com/nextrngbook/nextrngbook/issues
Project-URL: Documentation, https://nextrngbook.github.io/nextrngbook/
Keywords: pseudo-random number generation,pseudo-random number generator,PRNG,RNG,randomness,DX generator,Monte Carlo simulation,statistical simulation,statistical sampling
Classifier: Development Status :: 4 - Beta
Classifier: Intended Audience :: Developers
Classifier: Intended Audience :: End Users/Desktop
Classifier: Intended Audience :: Science/Research
Classifier: Programming Language :: C
Classifier: Programming Language :: Cython
Classifier: Programming Language :: Python :: 3
Classifier: Programming Language :: Python :: 3.9
Classifier: Programming Language :: Python :: 3.10
Classifier: Programming Language :: Python :: 3.11
Classifier: Programming Language :: Python :: 3.12
Classifier: Programming Language :: Python :: 3.13
Classifier: Operating System :: Microsoft :: Windows
Classifier: Operating System :: MacOS
Classifier: Operating System :: POSIX :: Linux
Classifier: Topic :: Software Development
Classifier: Topic :: Scientific/Engineering
Requires-Python: >=3.9
License-File: LICENSE
Requires-Dist: numpy<3,>=2.0.0
Dynamic: license-file
